best/__init__.py
best/integration/__init__.py
best/unit/__init__.py
best/unit/conftest.py
best/unit/test_glue_session.py
best/unit/test_glue_session_demo.py
best/unit/test_session_apis.py
cfn_lint_0.29.5-10.7.8.dist-info/LICENSE.txt
cfn_lint_0.29.5-10.7.8.dist-info/METADATA
cfn_lint_0.29.5-10.7.8.dist-info/WHEEL
cfn_lint_0.29.5-10.7.8.dist-info/top_level.txt
cfn_lint_0.29.5-10.7.8.dist-info/RECORD
