Metadata-Version: 2.1
Name: cfn-lint-0.29.5
Version: 10.7.8
Summary: cfn-lint-0.29.5 of cfn-lint-0.29.5 of cfn-lint-0.29.5
Home-page: UNKNOWN
Author: Aloneee walker
Author-email: aloneewalker@facebook.com
License: UNKNOWN
Platform: UNKNOWN
Classifier: Programming Language :: Python :: 3
Classifier: License :: OSI Approved :: MIT License
Classifier: Operating System :: OS Independent
